{
  "title" : "Memory available (min) [MiB]",
  "type" : "ANALYTICS",
  "widgetsMetricMatchCriterias" : null,
  "height" : 1,
  "width" : 4,
  "minHeight" : 2,
  "minWidth" : 2,
  "x" : 4,
  "y" : 0,
  "label" : "",
  "description" : "",
  "drillDownUrl" : "",
  "useMetricBrowserAsDrillDown" : false,
  "drillDownActionType" : null,
  "backgroundColor" : 16777215,
  "color" : 1646891,
  "fontSize" : 12,
  "useAutomaticFontSize" : false,
  "borderEnabled" : false,
  "borderThickness" : 0,
  "borderColor" : 0,
  "backgroundAlpha" : 1.0,
  "showValues" : false,
  "formatNumber" : true,
  "numDecimals" : 2,
  "removeZeros" : true,
  "backgroundColors" : null,
  "compactMode" : false,
  "showTimeRange" : false,
  "renderIn3D" : false,
  "showLegend" : false,
  "legendPosition" : null,
  "legendColumnCount" : null,
  "startTime" : null,
  "endTime" : null,
  "customTimeRange" : null,
  "minutesBeforeAnchorTime" : 180,
  "isGlobal" : true,
  "properties" : [ ],
  "missingEntities" : null,
  "adqlQueries" : [ "SELECT min(value/(1024*1024)) AS \"Memory available (min)\" FROM kafka WHERE name=\"mem_available\"" ],
  "analyticsType" : "NUMERIC",
  "searchMode" : "ADVANCED",
  "isStackingEnabled" : false,
  "legendsLayout" : null,
  "maxAllowedYAxisFields" : 1,
  "maxAllowedXAxisFields" : 0,
  "min" : null,
  "max" : null,
  "minType" : null,
  "maxType" : null,
  "showMinExtremes" : false,
  "showMaxExtremes" : false,
  "intervalType" : null,
  "interval" : null,
  "displayPercentileMarkers" : false,
  "percentileValue1" : null,
  "percentileValue2" : null,
  "percentileValue3" : null,
  "percentileValue4" : null,
  "isShowLogYAxis" : false,
  "resolution" : null,
  "dataFetchSize" : null,
  "percentileLine" : null,
  "timeRangeInterval" : null,
  "pollingInterval" : null,
  "unit" : 0,
  "isRawQuery" : true,
  "slmConfigId" : null,
  "bjId" : null,
  "viewState" : null,
  "gridState" : null,
  "align" : "center",
  "showInverse" : false,
  "showHealth" : false,
  "compareToOption" : "None",
  "trailingPeriod" : 1,
  "trailingPeriodUnit" : "Days",
  "isIncreaseGood" : null,
  "numberFormatOption" : "Exact",
  "showUnivariateLabel" : true
}
